eurelis_kb_framework/__init__.py
eurelis_kb_framework/base_factory.py
eurelis_kb_framework/class_loader.py
eurelis_kb_framework/gradiochat.py
eurelis_kb_framework/langchain_wrapper.py
eurelis_kb_framework/main.py
eurelis_kb_framework/types.py
eurelis_kb_framework/utils.py
eurelis_kb_framework/acronyms/__init__.py
eurelis_kb_framework/acronyms/acronyms_chain_wrapper.py
eurelis_kb_framework/acronyms/acronyms_document_transformer.py
eurelis_kb_framework/acronyms/acronyms_text_transformer.py
eurelis_kb_framework/addons/__init__.py
eurelis_kb_framework/addons/checker/__init__.py
eurelis_kb_framework/addons/checker/chat_checker.py
eurelis_kb_framework/addons/checker/check_input.py
eurelis_kb_framework/addons/checker/check_input_callback.py
eurelis_kb_framework/addons/checker/method.py
eurelis_kb_framework/addons/output/markdown_html_callback.py
eurelis_kb_framework/chains/__init__.py
eurelis_kb_framework/chains/conversational_retrieval/__init__.py
eurelis_kb_framework/dataset/__init__.py
eurelis_kb_framework/dataset/dataset.py
eurelis_kb_framework/document_loaders/__init__.py
eurelis_kb_framework/document_loaders/fs/__init__.py
eurelis_kb_framework/document_loaders/list/__init__.py
eurelis_kb_framework/document_loaders/list/list_loader.py
eurelis_kb_framework/document_loaders/sitemap/__init__.py
eurelis_kb_framework/document_loaders/url/__init__.py
eurelis_kb_framework/document_transformers/__init__.py
eurelis_kb_framework/document_transformers/base.py
eurelis_kb_framework/document_transformers/html2text/__init__.py
eurelis_kb_framework/document_transformers/urloutput/__init__.py
eurelis_kb_framework/embeddings/__init__.py
eurelis_kb_framework/embeddings/huggingface/__init__.py
eurelis_kb_framework/embeddings/openai/__init__.py
eurelis_kb_framework/llms/__init__.py
eurelis_kb_framework/llms/huggingface/__init__.py
eurelis_kb_framework/llms/openai/__init__.py
eurelis_kb_framework/memory/__init__.py
eurelis_kb_framework/memory/conversation_buffer_memory.py
eurelis_kb_framework-0.0.14.dist-info/LICENSE
eurelis_kb_framework-0.0.14.dist-info/METADATA
eurelis_kb_framework-0.0.14.dist-info/WHEEL
eurelis_kb_framework-0.0.14.dist-info/entry_points.txt
eurelis_kb_framework-0.0.14.dist-info/top_level.txt
eurelis_kb_framework-0.0.14.dist-info/RECORD
